abritamr/AmrSetup.py
abritamr/Collate.py
abritamr/Collate2.py
abritamr/CustomLog.py
abritamr/RunFinder.py
abritamr/Update.py
abritamr/__init__.py
abritamr/abritamr.py
abritamr/species_config.json
abritamr/version.py
abritamr/db/refgenes_latest.csv
abritamr/db/amrfinderplus/data/2024-07-22.1/AMR.LIB
abritamr/db/amrfinderplus/data/2024-07-22.1/AMR.LIB.h3f
abritamr/db/amrfinderplus/data/2024-07-22.1/AMR.LIB.h3i
abritamr/db/amrfinderplus/data/2024-07-22.1/AMR.LIB.h3m
abritamr/db/amrfinderplus/data/2024-07-22.1/AMR.LIB.h3p
abritamr/db/amrfinderplus/data/2024-07-22.1/AMRProt
abritamr/db/amrfinderplus/data/2024-07-22.1/AMRProt-mutation.tab
abritamr/db/amrfinderplus/data/2024-07-22.1/AMRProt-suppress
abritamr/db/amrfinderplus/data/2024-07-22.1/AMRProt-susceptible.tab
abritamr/db/amrfinderplus/data/2024-07-22.1/AMRProt.pdb
abritamr/db/amrfinderplus/data/2024-07-22.1/AMRProt.phr
abritamr/db/amrfinderplus/data/2024-07-22.1/AMRProt.pin
abritamr/db/amrfinderplus/data/2024-07-22.1/AMRProt.pjs
abritamr/db/amrfinderplus/data/2024-07-22.1/AMRProt.pot
abritamr/db/amrfinderplus/data/2024-07-22.1/AMRProt.psq
abritamr/db/amrfinderplus/data/2024-07-22.1/AMRProt.ptf
abritamr/db/amrfinderplus/data/2024-07-22.1/AMRProt.pto
abritamr/db/amrfinderplus/data/2024-07-22.1/AMR_CDS
abritamr/db/amrfinderplus/data/2024-07-22.1/AMR_CDS.ndb
abritamr/db/amrfinderplus/data/2024-07-22.1/AMR_CDS.nhr
abritamr/db/amrfinderplus/data/2024-07-22.1/AMR_CDS.nin
abritamr/db/amrfinderplus/data/2024-07-22.1/AMR_CDS.njs
abritamr/db/amrfinderplus/data/2024-07-22.1/AMR_CDS.not
abritamr/db/amrfinderplus/data/2024-07-22.1/AMR_CDS.nsq
abritamr/db/amrfinderplus/data/2024-07-22.1/AMR_CDS.ntf
abritamr/db/amrfinderplus/data/2024-07-22.1/AMR_CDS.nto
abritamr/db/amrfinderplus/data/2024-07-22.1/AMR_DNA-Acinetobacter_baumannii
abritamr/db/amrfinderplus/data/2024-07-22.1/AMR_DNA-Acinetobacter_baumannii.ndb
abritamr/db/amrfinderplus/data/2024-07-22.1/AMR_DNA-Acinetobacter_baumannii.nhr
abritamr-1.0.20.dist-info/METADATA
abritamr-1.0.20.dist-info/WHEEL
abritamr-1.0.20.dist-info/entry_points.txt
abritamr-1.0.20.dist-info/top_level.txt
abritamr-1.0.20.dist-info/RECORD
