Metadata-Version: 2.4
Name: abritamr
Version: 1.0.20
Summary: Running AMRFinderPlus for MDU
Home-page: https://github.com/MDU-PHL/abritamr
Author: Kristy Horan
Author-email: kristyhoran15@gmail.com
Maintainer: Kristy Horan
Maintainer-email: kristyhoran15@gmail.com
Classifier: Development Status :: 4 - Beta
Classifier: Programming Language :: Python :: Implementation :: CPython
Classifier: Intended Audience :: Science/Research
Classifier: License :: OSI Approved :: GNU General Public License v3 (GPLv3)
Classifier: Natural Language :: English
Classifier: Programming Language :: Python :: 3 :: Only
Classifier: Programming Language :: Python :: 3.6
Classifier: Programming Language :: Python :: 3.7
Classifier: Programming Language :: Python :: 3.9
Classifier: Topic :: Scientific/Engineering :: Bio-Informatics
Requires-Python: >=3.9, <4
Requires-Dist: pandas
Requires-Dist: xlsxwriter
Dynamic: author
Dynamic: author-email
Dynamic: classifier
Dynamic: description
Dynamic: description-content-type
Dynamic: home-page
Dynamic: maintainer
Dynamic: maintainer-email
Dynamic: requires-dist
Dynamic: requires-python
Dynamic: summary
